{"name":"Title of your scenario","id":"login-exitoso;title-of-your-scenario","testSteps":[{"number":1,"description":"Given \"Ivan\" se encuentra en la pagina del login\r\n| url | https://www.saucedemo.com/ |\r\n| userName | standard_user |\r\n| password | secret_sauce |","duration":6768,"startTime":"2022-07-15T18:16:40.331-05:00[America/Bogota]","screenshots":[{"screenshot":"dd47454da0f27cf713822ba905d35221d1d3dd88c9da280118379d132c4ef212.png","timeStamp":1657927007099}],"result":"SUCCESS","precondition":false,"level":0,"children":[{"number":2,"description":"Ivan saucedemo login","duration":6407,"startTime":"2022-07-15T18:16:40.681-05:00[America/Bogota]","screenshots":[{"screenshot":"dd47454da0f27cf713822ba905d35221d1d3dd88c9da280118379d132c4ef212.png","timeStamp":1657927007088}],"result":"SUCCESS","precondition":false,"level":1,"children":[{"number":3,"description":"Ivan opens the https://www.saucedemo.com/","duration":4464,"startTime":"2022-07-15T18:16:40.744-05:00[America/Bogota]","screenshots":[{"screenshot":"5803702b275284a1fd042297e401c3626df3b075b9594336deebf67740ee6153.png","timeStamp":1657927005207}],"result":"SUCCESS","precondition":false,"level":2},{"number":4,"description":"Ivan enters \u0027standard_user\u0027 into Nombre Usuario","duration":536,"startTime":"2022-07-15T18:16:45.214-05:00[America/Bogota]","screenshots":[{"screenshot":"5803702b275284a1fd042297e401c3626df3b075b9594336deebf67740ee6153.png","timeStamp":1657927005219},{"screenshot":"1399787b6c7ac7ec09ce737cffeb99fea46073a7512ae9befd5d1566dac6a0e1.png","timeStamp":1657927005749}],"result":"SUCCESS","precondition":false,"level":2},{"number":5,"description":"Ivan enters \u0027secret_sauce\u0027 into Password","duration":427,"startTime":"2022-07-15T18:16:45.751-05:00[America/Bogota]","screenshots":[{"screenshot":"1399787b6c7ac7ec09ce737cffeb99fea46073a7512ae9befd5d1566dac6a0e1.png","timeStamp":1657927005757},{"screenshot":"159b5a8567d3e80560a4ca00bc377dae367a8f81d6dc095886a6d96cc981b514.png","timeStamp":1657927006178}],"result":"SUCCESS","precondition":false,"level":2},{"number":6,"description":"Ivan clicks on Submit","duration":904,"startTime":"2022-07-15T18:16:46.180-05:00[America/Bogota]","screenshots":[{"screenshot":"159b5a8567d3e80560a4ca00bc377dae367a8f81d6dc095886a6d96cc981b514.png","timeStamp":1657927006184},{"screenshot":"dd47454da0f27cf713822ba905d35221d1d3dd88c9da280118379d132c4ef212.png","timeStamp":1657927007083}],"result":"SUCCESS","precondition":false,"level":2}]}]},{"number":7,"description":"When llena los campos","duration":6,"startTime":"2022-07-15T18:16:47.100-05:00[America/Bogota]","screenshots":[{"screenshot":"dd47454da0f27cf713822ba905d35221d1d3dd88c9da280118379d132c4ef212.png","timeStamp":1657927007106}],"result":"SUCCESS","precondition":false,"level":0},{"number":8,"description":"Then Visualiza la lista de productos","duration":9,"startTime":"2022-07-15T18:16:47.107-05:00[America/Bogota]","screenshots":[{"screenshot":"dd47454da0f27cf713822ba905d35221d1d3dd88c9da280118379d132c4ef212.png","timeStamp":1657927007116}],"result":"SUCCESS","precondition":false,"level":0}],"userStory":{"id":"login-exitoso","storyName":"Login Exitoso","path":"saucedemologin.feature","narrative":"  I want to use this template for my feature file","type":"feature"},"featureTag":{"name":"Login Exitoso","type":"feature","displayName":"Login Exitoso"},"title":"Title of your scenario","description":"","tags":[{"name":"tag1","type":"tag","displayName":"tag1"},{"name":"tag","type":"tag","displayName":"tag"}],"startTime":"2022-07-15T18:16:40.205-05:00[America/Bogota]","duration":6915,"projectKey":"","sessionId":"2bd69cd684a053944c64538d05b893b1","driver":"chrome:ivan","isManualTestingUpToDate":false,"manual":false,"testSource":"Cucumber","actors":[{"name":"Ivan","can":["browse the web"]}],"result":"SUCCESS"}