{"name":"Inventario","id":"title-of-your-feature;inventario","testSteps":[{"number":1,"description":"Given \"standard_user\" se encuentra en la pagina inventarios\r\n| url | https://www.saucedemo.com/inventory.html |","duration":13601,"startTime":"2022-07-15T20:47:21.954-05:00[America/Bogota]","exception":{"errorType":"net.thucydides.core.webdriver.exceptions.ElementShouldBePresentException","message":"Expected condition failed: waiting for By.xpath: //button[@id\u003d\u0027add-to-cart-sauce-labs-backpack\u0027] to be present (tried for 5 second(s) with 100 milliseconds interval)\nBuild info: version: \u00273.141.59\u0027, revision: \u0027e82be7d358\u0027, time: \u00272018-11-14T08:17:03\u0027\nSystem info: host: \u0027SSMED5CG1100JRZ\u0027, ip: \u0027192.168.1.145\u0027, os.name: \u0027Windows 10\u0027, os.arch: \u0027amd64\u0027, os.version: \u002710.0\u0027, java.version: \u00271.8.0_333\u0027\nDriver info: driver.version: unknown","stackTrace":[{"declaringClass":"com.sophos.semillero.tasks.NewProductListSauceDemo","methodName":"performAs","fileName":"NewProductListSauceDemo.java","lineNumber":28},{"declaringClass":"com.sophos.semillero.stepdefinitions.ProducListSauceDemoStepDefinitions","methodName":"elUsuarioSeEncuentraEnLaPaginaInventarios","fileName":"ProducListSauceDemoStepDefinitions.java","lineNumber":23},{"declaringClass":"io.cucumber.java.Invoker","methodName":"doInvoke","fileName":"Invoker.java","lineNumber":66},{"declaringClass":"io.cucumber.java.Invoker","methodName":"invoke","fileName":"Invoker.java","lineNumber":24},{"declaringClass":"io.cucumber.java.AbstractGlueDefinition","methodName":"invokeMethod","fileName":"AbstractGlueDefinition.java","lineNumber":47},{"declaringClass":"io.cucumber.java.JavaStepDefinition","methodName":"execute","fileName":"JavaStepDefinition.java","lineNumber":29},{"declaringClass":"io.cucumber.core.runner.CoreStepDefinition","methodName":"execute","fileName":"CoreStepDefinition.java","lineNumber":66},{"declaringClass":"io.cucumber.core.runner.PickleStepDefinitionMatch","methodName":"runStep","fileName":"PickleStepDefinitionMatch.java","lineNumber":63},{"declaringClass":"io.cucumber.core.runner.TestStep","methodName":"executeStep","fileName":"TestStep.java","lineNumber":92},{"declaringClass":"io.cucumber.core.runner.TestStep","methodName":"run","fileName":"TestStep.java","lineNumber":64},{"declaringClass":"io.cucumber.core.runner.PickleStepTestStep","methodName":"run","fileName":"PickleStepTestStep.java","lineNumber":51},{"declaringClass":"io.cucumber.core.runner.TestCase","methodName":"run","fileName":"TestCase.java","lineNumber":104},{"declaringClass":"io.cucumber.core.runner.Runner","methodName":"runPickle","fileName":"Runner.java","lineNumber":73},{"declaringClass":"io.cucumber.junit.FeatureRunner","methodName":"runChild","fileName":"FeatureRunner.java","lineNumber":135},{"declaringClass":"io.cucumber.junit.FeatureRunner","methodName":"runChild","fileName":"FeatureRunner.java","lineNumber":27},{"declaringClass":"io.cucumber.junit.CucumberSerenityRunner","methodName":"runChild","fileName":"CucumberSerenityRunner.java","lineNumber":258},{"declaringClass":"io.cucumber.junit.CucumberSerenityRunner","methodName":"runChild","fileName":"CucumberSerenityRunner.java","lineNumber":57},{"declaringClass":"org.eclipse.jdt.internal.junit4.runner.JUnit4TestReference","methodName":"run","fileName":"JUnit4TestReference.java","lineNumber":93},{"declaringClass":"org.eclipse.jdt.internal.junit.runner.TestExecution","methodName":"run","fileName":"TestExecution.java","lineNumber":40},{"declaringClass":"org.eclipse.jdt.internal.junit.runner.RemoteTestRunner","methodName":"runTests","fileName":"RemoteTestRunner.java","lineNumber":529},{"declaringClass":"org.eclipse.jdt.internal.junit.runner.RemoteTestRunner","methodName":"runTests","fileName":"RemoteTestRunner.java","lineNumber":756},{"declaringClass":"org.eclipse.jdt.internal.junit.runner.RemoteTestRunner","methodName":"run","fileName":"RemoteTestRunner.java","lineNumber":452},{"declaringClass":"org.eclipse.jdt.internal.junit.runner.RemoteTestRunner","methodName":"main","fileName":"RemoteTestRunner.java","lineNumber":210}],"rootCause":{"errorType":"org.openqa.selenium.TimeoutException","message":"Expected condition failed: waiting for By.xpath: //button[@id\u003d\u0027add-to-cart-sauce-labs-backpack\u0027] to be present (tried for 5 second(s) with 100 milliseconds interval)\nBuild info: version: \u00273.141.59\u0027, revision: \u0027e82be7d358\u0027, time: \u00272018-11-14T08:17:03\u0027\nSystem info: host: \u0027SSMED5CG1100JRZ\u0027, ip: \u0027192.168.1.145\u0027, os.name: \u0027Windows 10\u0027, os.arch: \u0027amd64\u0027, os.version: \u002710.0\u0027, java.version: \u00271.8.0_333\u0027\nDriver info: driver.version: unknown","stackTrace":[{"declaringClass":"com.sophos.semillero.tasks.NewProductListSauceDemo","methodName":"performAs","fileName":"NewProductListSauceDemo.java","lineNumber":28},{"declaringClass":"com.sophos.semillero.stepdefinitions.ProducListSauceDemoStepDefinitions","methodName":"elUsuarioSeEncuentraEnLaPaginaInventarios","fileName":"ProducListSauceDemoStepDefinitions.java","lineNumber":23},{"declaringClass":"io.cucumber.java.Invoker","methodName":"doInvoke","fileName":"Invoker.java","lineNumber":66},{"declaringClass":"io.cucumber.java.Invoker","methodName":"invoke","fileName":"Invoker.java","lineNumber":24},{"declaringClass":"io.cucumber.java.AbstractGlueDefinition","methodName":"invokeMethod","fileName":"AbstractGlueDefinition.java","lineNumber":47},{"declaringClass":"io.cucumber.java.JavaStepDefinition","methodName":"execute","fileName":"JavaStepDefinition.java","lineNumber":29},{"declaringClass":"io.cucumber.core.runner.CoreStepDefinition","methodName":"execute","fileName":"CoreStepDefinition.java","lineNumber":66},{"declaringClass":"io.cucumber.core.runner.PickleStepDefinitionMatch","methodName":"runStep","fileName":"PickleStepDefinitionMatch.java","lineNumber":63},{"declaringClass":"io.cucumber.core.runner.TestStep","methodName":"executeStep","fileName":"TestStep.java","lineNumber":92},{"declaringClass":"io.cucumber.core.runner.TestStep","methodName":"run","fileName":"TestStep.java","lineNumber":64},{"declaringClass":"io.cucumber.core.runner.PickleStepTestStep","methodName":"run","fileName":"PickleStepTestStep.java","lineNumber":51},{"declaringClass":"io.cucumber.core.runner.TestCase","methodName":"run","fileName":"TestCase.java","lineNumber":104},{"declaringClass":"io.cucumber.core.runner.Runner","methodName":"runPickle","fileName":"Runner.java","lineNumber":73},{"declaringClass":"io.cucumber.junit.FeatureRunner","methodName":"runChild","fileName":"FeatureRunner.java","lineNumber":135},{"declaringClass":"io.cucumber.junit.FeatureRunner","methodName":"runChild","fileName":"FeatureRunner.java","lineNumber":27},{"declaringClass":"io.cucumber.junit.CucumberSerenityRunner","methodName":"runChild","fileName":"CucumberSerenityRunner.java","lineNumber":258},{"declaringClass":"io.cucumber.junit.CucumberSerenityRunner","methodName":"runChild","fileName":"CucumberSerenityRunner.java","lineNumber":57},{"declaringClass":"org.eclipse.jdt.internal.junit4.runner.JUnit4TestReference","methodName":"run","fileName":"JUnit4TestReference.java","lineNumber":93},{"declaringClass":"org.eclipse.jdt.internal.junit.runner.TestExecution","methodName":"run","fileName":"TestExecution.java","lineNumber":40},{"declaringClass":"org.eclipse.jdt.internal.junit.runner.RemoteTestRunner","methodName":"runTests","fileName":"RemoteTestRunner.java","lineNumber":529},{"declaringClass":"org.eclipse.jdt.internal.junit.runner.RemoteTestRunner","methodName":"runTests","fileName":"RemoteTestRunner.java","lineNumber":756},{"declaringClass":"org.eclipse.jdt.internal.junit.runner.RemoteTestRunner","methodName":"run","fileName":"RemoteTestRunner.java","lineNumber":452},{"declaringClass":"org.eclipse.jdt.internal.junit.runner.RemoteTestRunner","methodName":"main","fileName":"RemoteTestRunner.java","lineNumber":210}]}},"result":"FAILURE","precondition":false,"level":0,"children":[{"number":2,"description":"Standard_user new product list sauce demo","duration":13158,"startTime":"2022-07-15T20:47:22.391-05:00[America/Bogota]","exception":{"errorType":"net.thucydides.core.webdriver.exceptions.ElementShouldBePresentException","message":"Expected condition failed: waiting for By.xpath: //button[@id\u003d\u0027add-to-cart-sauce-labs-backpack\u0027] to be present (tried for 5 second(s) with 100 milliseconds interval)\nBuild info: version: \u00273.141.59\u0027, revision: \u0027e82be7d358\u0027, time: \u00272018-11-14T08:17:03\u0027\nSystem info: host: \u0027SSMED5CG1100JRZ\u0027, ip: \u0027192.168.1.145\u0027, os.name: \u0027Windows 10\u0027, os.arch: \u0027amd64\u0027, os.version: \u002710.0\u0027, java.version: \u00271.8.0_333\u0027\nDriver info: driver.version: unknown","stackTrace":[{"declaringClass":"com.sophos.semillero.tasks.NewProductListSauceDemo","methodName":"performAs","fileName":"NewProductListSauceDemo.java","lineNumber":28},{"declaringClass":"com.sophos.semillero.stepdefinitions.ProducListSauceDemoStepDefinitions","methodName":"elUsuarioSeEncuentraEnLaPaginaInventarios","fileName":"ProducListSauceDemoStepDefinitions.java","lineNumber":23},{"declaringClass":"io.cucumber.java.Invoker","methodName":"doInvoke","fileName":"Invoker.java","lineNumber":66},{"declaringClass":"io.cucumber.java.Invoker","methodName":"invoke","fileName":"Invoker.java","lineNumber":24},{"declaringClass":"io.cucumber.java.AbstractGlueDefinition","methodName":"invokeMethod","fileName":"AbstractGlueDefinition.java","lineNumber":47},{"declaringClass":"io.cucumber.java.JavaStepDefinition","methodName":"execute","fileName":"JavaStepDefinition.java","lineNumber":29},{"declaringClass":"io.cucumber.core.runner.CoreStepDefinition","methodName":"execute","fileName":"CoreStepDefinition.java","lineNumber":66},{"declaringClass":"io.cucumber.core.runner.PickleStepDefinitionMatch","methodName":"runStep","fileName":"PickleStepDefinitionMatch.java","lineNumber":63},{"declaringClass":"io.cucumber.core.runner.TestStep","methodName":"executeStep","fileName":"TestStep.java","lineNumber":92},{"declaringClass":"io.cucumber.core.runner.TestStep","methodName":"run","fileName":"TestStep.java","lineNumber":64},{"declaringClass":"io.cucumber.core.runner.PickleStepTestStep","methodName":"run","fileName":"PickleStepTestStep.java","lineNumber":51},{"declaringClass":"io.cucumber.core.runner.TestCase","methodName":"run","fileName":"TestCase.java","lineNumber":104},{"declaringClass":"io.cucumber.core.runner.Runner","methodName":"runPickle","fileName":"Runner.java","lineNumber":73},{"declaringClass":"io.cucumber.junit.FeatureRunner","methodName":"runChild","fileName":"FeatureRunner.java","lineNumber":135},{"declaringClass":"io.cucumber.junit.FeatureRunner","methodName":"runChild","fileName":"FeatureRunner.java","lineNumber":27},{"declaringClass":"io.cucumber.junit.CucumberSerenityRunner","methodName":"runChild","fileName":"CucumberSerenityRunner.java","lineNumber":258},{"declaringClass":"io.cucumber.junit.CucumberSerenityRunner","methodName":"runChild","fileName":"CucumberSerenityRunner.java","lineNumber":57},{"declaringClass":"org.eclipse.jdt.internal.junit4.runner.JUnit4TestReference","methodName":"run","fileName":"JUnit4TestReference.java","lineNumber":93},{"declaringClass":"org.eclipse.jdt.internal.junit.runner.TestExecution","methodName":"run","fileName":"TestExecution.java","lineNumber":40},{"declaringClass":"org.eclipse.jdt.internal.junit.runner.RemoteTestRunner","methodName":"runTests","fileName":"RemoteTestRunner.java","lineNumber":529},{"declaringClass":"org.eclipse.jdt.internal.junit.runner.RemoteTestRunner","methodName":"runTests","fileName":"RemoteTestRunner.java","lineNumber":756},{"declaringClass":"org.eclipse.jdt.internal.junit.runner.RemoteTestRunner","methodName":"run","fileName":"RemoteTestRunner.java","lineNumber":452},{"declaringClass":"org.eclipse.jdt.internal.junit.runner.RemoteTestRunner","methodName":"main","fileName":"RemoteTestRunner.java","lineNumber":210}],"rootCause":{"errorType":"org.openqa.selenium.TimeoutException","message":"Expected condition failed: waiting for By.xpath: //button[@id\u003d\u0027add-to-cart-sauce-labs-backpack\u0027] to be present (tried for 5 second(s) with 100 milliseconds interval)\nBuild info: version: \u00273.141.59\u0027, revision: \u0027e82be7d358\u0027, time: \u00272018-11-14T08:17:03\u0027\nSystem info: host: \u0027SSMED5CG1100JRZ\u0027, ip: \u0027192.168.1.145\u0027, os.name: \u0027Windows 10\u0027, os.arch: \u0027amd64\u0027, os.version: \u002710.0\u0027, java.version: \u00271.8.0_333\u0027\nDriver info: driver.version: unknown","stackTrace":[{"declaringClass":"com.sophos.semillero.tasks.NewProductListSauceDemo","methodName":"performAs","fileName":"NewProductListSauceDemo.java","lineNumber":28},{"declaringClass":"com.sophos.semillero.stepdefinitions.ProducListSauceDemoStepDefinitions","methodName":"elUsuarioSeEncuentraEnLaPaginaInventarios","fileName":"ProducListSauceDemoStepDefinitions.java","lineNumber":23},{"declaringClass":"io.cucumber.java.Invoker","methodName":"doInvoke","fileName":"Invoker.java","lineNumber":66},{"declaringClass":"io.cucumber.java.Invoker","methodName":"invoke","fileName":"Invoker.java","lineNumber":24},{"declaringClass":"io.cucumber.java.AbstractGlueDefinition","methodName":"invokeMethod","fileName":"AbstractGlueDefinition.java","lineNumber":47},{"declaringClass":"io.cucumber.java.JavaStepDefinition","methodName":"execute","fileName":"JavaStepDefinition.java","lineNumber":29},{"declaringClass":"io.cucumber.core.runner.CoreStepDefinition","methodName":"execute","fileName":"CoreStepDefinition.java","lineNumber":66},{"declaringClass":"io.cucumber.core.runner.PickleStepDefinitionMatch","methodName":"runStep","fileName":"PickleStepDefinitionMatch.java","lineNumber":63},{"declaringClass":"io.cucumber.core.runner.TestStep","methodName":"executeStep","fileName":"TestStep.java","lineNumber":92},{"declaringClass":"io.cucumber.core.runner.TestStep","methodName":"run","fileName":"TestStep.java","lineNumber":64},{"declaringClass":"io.cucumber.core.runner.PickleStepTestStep","methodName":"run","fileName":"PickleStepTestStep.java","lineNumber":51},{"declaringClass":"io.cucumber.core.runner.TestCase","methodName":"run","fileName":"TestCase.java","lineNumber":104},{"declaringClass":"io.cucumber.core.runner.Runner","methodName":"runPickle","fileName":"Runner.java","lineNumber":73},{"declaringClass":"io.cucumber.junit.FeatureRunner","methodName":"runChild","fileName":"FeatureRunner.java","lineNumber":135},{"declaringClass":"io.cucumber.junit.FeatureRunner","methodName":"runChild","fileName":"FeatureRunner.java","lineNumber":27},{"declaringClass":"io.cucumber.junit.CucumberSerenityRunner","methodName":"runChild","fileName":"CucumberSerenityRunner.java","lineNumber":258},{"declaringClass":"io.cucumber.junit.CucumberSerenityRunner","methodName":"runChild","fileName":"CucumberSerenityRunner.java","lineNumber":57},{"declaringClass":"org.eclipse.jdt.internal.junit4.runner.JUnit4TestReference","methodName":"run","fileName":"JUnit4TestReference.java","lineNumber":93},{"declaringClass":"org.eclipse.jdt.internal.junit.runner.TestExecution","methodName":"run","fileName":"TestExecution.java","lineNumber":40},{"declaringClass":"org.eclipse.jdt.internal.junit.runner.RemoteTestRunner","methodName":"runTests","fileName":"RemoteTestRunner.java","lineNumber":529},{"declaringClass":"org.eclipse.jdt.internal.junit.runner.RemoteTestRunner","methodName":"runTests","fileName":"RemoteTestRunner.java","lineNumber":756},{"declaringClass":"org.eclipse.jdt.internal.junit.runner.RemoteTestRunner","methodName":"run","fileName":"RemoteTestRunner.java","lineNumber":452},{"declaringClass":"org.eclipse.jdt.internal.junit.runner.RemoteTestRunner","methodName":"main","fileName":"RemoteTestRunner.java","lineNumber":210}]}},"result":"FAILURE","precondition":false,"level":1,"children":[{"number":3,"description":"standard_user opens the https://www.saucedemo.com/inventory.html","duration":6323,"startTime":"2022-07-15T20:47:22.432-05:00[America/Bogota]","screenshots":[{"screenshot":"38dfe1dd0d4aecd118ee9dc61d049699f6b838f674c3eba94557294d44f19512.png","timeStamp":1657936048754}],"result":"SUCCESS","precondition":false,"level":2},{"number":4,"description":"standard_user clicks on agregar1","duration":6782,"startTime":"2022-07-15T20:47:28.762-05:00[America/Bogota]","screenshots":[{"screenshot":"38dfe1dd0d4aecd118ee9dc61d049699f6b838f674c3eba94557294d44f19512.png","timeStamp":1657936048768},{"screenshot":"38dfe1dd0d4aecd118ee9dc61d049699f6b838f674c3eba94557294d44f19512.png","htmlSource":"pagesource1952995118025629355.html.txt","timeStamp":1657936055538}],"exception":{"errorType":"net.thucydides.core.webdriver.exceptions.ElementShouldBePresentException","message":"Expected condition failed: waiting for By.xpath: //button[@id\u003d\u0027add-to-cart-sauce-labs-backpack\u0027] to be present (tried for 5 second(s) with 100 milliseconds interval)\nBuild info: version: \u00273.141.59\u0027, revision: \u0027e82be7d358\u0027, time: \u00272018-11-14T08:17:03\u0027\nSystem info: host: \u0027SSMED5CG1100JRZ\u0027, ip: \u0027192.168.1.145\u0027, os.name: \u0027Windows 10\u0027, os.arch: \u0027amd64\u0027, os.version: \u002710.0\u0027, java.version: \u00271.8.0_333\u0027\nDriver info: driver.version: unknown","stackTrace":[{"declaringClass":"com.sophos.semillero.tasks.NewProductListSauceDemo","methodName":"performAs","fileName":"NewProductListSauceDemo.java","lineNumber":28},{"declaringClass":"com.sophos.semillero.stepdefinitions.ProducListSauceDemoStepDefinitions","methodName":"elUsuarioSeEncuentraEnLaPaginaInventarios","fileName":"ProducListSauceDemoStepDefinitions.java","lineNumber":23},{"declaringClass":"io.cucumber.java.Invoker","methodName":"doInvoke","fileName":"Invoker.java","lineNumber":66},{"declaringClass":"io.cucumber.java.Invoker","methodName":"invoke","fileName":"Invoker.java","lineNumber":24},{"declaringClass":"io.cucumber.java.AbstractGlueDefinition","methodName":"invokeMethod","fileName":"AbstractGlueDefinition.java","lineNumber":47},{"declaringClass":"io.cucumber.java.JavaStepDefinition","methodName":"execute","fileName":"JavaStepDefinition.java","lineNumber":29},{"declaringClass":"io.cucumber.core.runner.CoreStepDefinition","methodName":"execute","fileName":"CoreStepDefinition.java","lineNumber":66},{"declaringClass":"io.cucumber.core.runner.PickleStepDefinitionMatch","methodName":"runStep","fileName":"PickleStepDefinitionMatch.java","lineNumber":63},{"declaringClass":"io.cucumber.core.runner.TestStep","methodName":"executeStep","fileName":"TestStep.java","lineNumber":92},{"declaringClass":"io.cucumber.core.runner.TestStep","methodName":"run","fileName":"TestStep.java","lineNumber":64},{"declaringClass":"io.cucumber.core.runner.PickleStepTestStep","methodName":"run","fileName":"PickleStepTestStep.java","lineNumber":51},{"declaringClass":"io.cucumber.core.runner.TestCase","methodName":"run","fileName":"TestCase.java","lineNumber":104},{"declaringClass":"io.cucumber.core.runner.Runner","methodName":"runPickle","fileName":"Runner.java","lineNumber":73},{"declaringClass":"io.cucumber.junit.FeatureRunner","methodName":"runChild","fileName":"FeatureRunner.java","lineNumber":135},{"declaringClass":"io.cucumber.junit.FeatureRunner","methodName":"runChild","fileName":"FeatureRunner.java","lineNumber":27},{"declaringClass":"io.cucumber.junit.CucumberSerenityRunner","methodName":"runChild","fileName":"CucumberSerenityRunner.java","lineNumber":258},{"declaringClass":"io.cucumber.junit.CucumberSerenityRunner","methodName":"runChild","fileName":"CucumberSerenityRunner.java","lineNumber":57},{"declaringClass":"org.eclipse.jdt.internal.junit4.runner.JUnit4TestReference","methodName":"run","fileName":"JUnit4TestReference.java","lineNumber":93},{"declaringClass":"org.eclipse.jdt.internal.junit.runner.TestExecution","methodName":"run","fileName":"TestExecution.java","lineNumber":40},{"declaringClass":"org.eclipse.jdt.internal.junit.runner.RemoteTestRunner","methodName":"runTests","fileName":"RemoteTestRunner.java","lineNumber":529},{"declaringClass":"org.eclipse.jdt.internal.junit.runner.RemoteTestRunner","methodName":"runTests","fileName":"RemoteTestRunner.java","lineNumber":756},{"declaringClass":"org.eclipse.jdt.internal.junit.runner.RemoteTestRunner","methodName":"run","fileName":"RemoteTestRunner.java","lineNumber":452},{"declaringClass":"org.eclipse.jdt.internal.junit.runner.RemoteTestRunner","methodName":"main","fileName":"RemoteTestRunner.java","lineNumber":210}],"rootCause":{"errorType":"org.openqa.selenium.TimeoutException","message":"Expected condition failed: waiting for By.xpath: //button[@id\u003d\u0027add-to-cart-sauce-labs-backpack\u0027] to be present (tried for 5 second(s) with 100 milliseconds interval)\nBuild info: version: \u00273.141.59\u0027, revision: \u0027e82be7d358\u0027, time: \u00272018-11-14T08:17:03\u0027\nSystem info: host: \u0027SSMED5CG1100JRZ\u0027, ip: \u0027192.168.1.145\u0027, os.name: \u0027Windows 10\u0027, os.arch: \u0027amd64\u0027, os.version: \u002710.0\u0027, java.version: \u00271.8.0_333\u0027\nDriver info: driver.version: unknown","stackTrace":[{"declaringClass":"com.sophos.semillero.tasks.NewProductListSauceDemo","methodName":"performAs","fileName":"NewProductListSauceDemo.java","lineNumber":28},{"declaringClass":"com.sophos.semillero.stepdefinitions.ProducListSauceDemoStepDefinitions","methodName":"elUsuarioSeEncuentraEnLaPaginaInventarios","fileName":"ProducListSauceDemoStepDefinitions.java","lineNumber":23},{"declaringClass":"io.cucumber.java.Invoker","methodName":"doInvoke","fileName":"Invoker.java","lineNumber":66},{"declaringClass":"io.cucumber.java.Invoker","methodName":"invoke","fileName":"Invoker.java","lineNumber":24},{"declaringClass":"io.cucumber.java.AbstractGlueDefinition","methodName":"invokeMethod","fileName":"AbstractGlueDefinition.java","lineNumber":47},{"declaringClass":"io.cucumber.java.JavaStepDefinition","methodName":"execute","fileName":"JavaStepDefinition.java","lineNumber":29},{"declaringClass":"io.cucumber.core.runner.CoreStepDefinition","methodName":"execute","fileName":"CoreStepDefinition.java","lineNumber":66},{"declaringClass":"io.cucumber.core.runner.PickleStepDefinitionMatch","methodName":"runStep","fileName":"PickleStepDefinitionMatch.java","lineNumber":63},{"declaringClass":"io.cucumber.core.runner.TestStep","methodName":"executeStep","fileName":"TestStep.java","lineNumber":92},{"declaringClass":"io.cucumber.core.runner.TestStep","methodName":"run","fileName":"TestStep.java","lineNumber":64},{"declaringClass":"io.cucumber.core.runner.PickleStepTestStep","methodName":"run","fileName":"PickleStepTestStep.java","lineNumber":51},{"declaringClass":"io.cucumber.core.runner.TestCase","methodName":"run","fileName":"TestCase.java","lineNumber":104},{"declaringClass":"io.cucumber.core.runner.Runner","methodName":"runPickle","fileName":"Runner.java","lineNumber":73},{"declaringClass":"io.cucumber.junit.FeatureRunner","methodName":"runChild","fileName":"FeatureRunner.java","lineNumber":135},{"declaringClass":"io.cucumber.junit.FeatureRunner","methodName":"runChild","fileName":"FeatureRunner.java","lineNumber":27},{"declaringClass":"io.cucumber.junit.CucumberSerenityRunner","methodName":"runChild","fileName":"CucumberSerenityRunner.java","lineNumber":258},{"declaringClass":"io.cucumber.junit.CucumberSerenityRunner","methodName":"runChild","fileName":"CucumberSerenityRunner.java","lineNumber":57},{"declaringClass":"org.eclipse.jdt.internal.junit4.runner.JUnit4TestReference","methodName":"run","fileName":"JUnit4TestReference.java","lineNumber":93},{"declaringClass":"org.eclipse.jdt.internal.junit.runner.TestExecution","methodName":"run","fileName":"TestExecution.java","lineNumber":40},{"declaringClass":"org.eclipse.jdt.internal.junit.runner.RemoteTestRunner","methodName":"runTests","fileName":"RemoteTestRunner.java","lineNumber":529},{"declaringClass":"org.eclipse.jdt.internal.junit.runner.RemoteTestRunner","methodName":"runTests","fileName":"RemoteTestRunner.java","lineNumber":756},{"declaringClass":"org.eclipse.jdt.internal.junit.runner.RemoteTestRunner","methodName":"run","fileName":"RemoteTestRunner.java","lineNumber":452},{"declaringClass":"org.eclipse.jdt.internal.junit.runner.RemoteTestRunner","methodName":"main","fileName":"RemoteTestRunner.java","lineNumber":210}]}},"result":"FAILURE","precondition":false,"level":2}]}]},{"number":5,"description":"When Ingresa a la lista de articulos","duration":5,"startTime":"2022-07-15T20:47:35.576-05:00[America/Bogota]","result":"SKIPPED","precondition":false,"level":0},{"number":6,"description":"Then agrega 2 articulos al carrito \"exitoso\"","duration":4,"startTime":"2022-07-15T20:47:35.582-05:00[America/Bogota]","result":"SKIPPED","precondition":false,"level":0}],"userStory":{"id":"title-of-your-feature","storyName":"Title of your feature","path":"10.feature","narrative":"  I want to use this template for my feature file","type":"feature"},"featureTag":{"name":"Title of your feature","type":"feature","displayName":"Title of your feature"},"title":"Inventario","description":"","tags":[{"name":"tag2","type":"tag","displayName":"tag2"}],"startTime":"2022-07-15T20:47:21.797-05:00[America/Bogota]","duration":13797,"testFailureCause":{"errorType":"net.thucydides.core.webdriver.exceptions.ElementShouldBePresentException","message":"Expected condition failed: waiting for By.xpath: //button[@id\u003d\u0027add-to-cart-sauce-labs-backpack\u0027] to be present (tried for 5 second(s) with 100 milliseconds interval)\nBuild info: version: \u00273.141.59\u0027, revision: \u0027e82be7d358\u0027, time: \u00272018-11-14T08:17:03\u0027\nSystem info: host: \u0027SSMED5CG1100JRZ\u0027, ip: \u0027192.168.1.145\u0027, os.name: \u0027Windows 10\u0027, os.arch: \u0027amd64\u0027, os.version: \u002710.0\u0027, java.version: \u00271.8.0_333\u0027\nDriver info: driver.version: unknown","stackTrace":[{"declaringClass":"com.sophos.semillero.tasks.NewProductListSauceDemo","methodName":"performAs","fileName":"NewProductListSauceDemo.java","lineNumber":28},{"declaringClass":"com.sophos.semillero.stepdefinitions.ProducListSauceDemoStepDefinitions","methodName":"elUsuarioSeEncuentraEnLaPaginaInventarios","fileName":"ProducListSauceDemoStepDefinitions.java","lineNumber":23},{"declaringClass":"io.cucumber.java.Invoker","methodName":"doInvoke","fileName":"Invoker.java","lineNumber":66},{"declaringClass":"io.cucumber.java.Invoker","methodName":"invoke","fileName":"Invoker.java","lineNumber":24},{"declaringClass":"io.cucumber.java.AbstractGlueDefinition","methodName":"invokeMethod","fileName":"AbstractGlueDefinition.java","lineNumber":47},{"declaringClass":"io.cucumber.java.JavaStepDefinition","methodName":"execute","fileName":"JavaStepDefinition.java","lineNumber":29},{"declaringClass":"io.cucumber.core.runner.CoreStepDefinition","methodName":"execute","fileName":"CoreStepDefinition.java","lineNumber":66},{"declaringClass":"io.cucumber.core.runner.PickleStepDefinitionMatch","methodName":"runStep","fileName":"PickleStepDefinitionMatch.java","lineNumber":63},{"declaringClass":"io.cucumber.core.runner.TestStep","methodName":"executeStep","fileName":"TestStep.java","lineNumber":92},{"declaringClass":"io.cucumber.core.runner.TestStep","methodName":"run","fileName":"TestStep.java","lineNumber":64},{"declaringClass":"io.cucumber.core.runner.PickleStepTestStep","methodName":"run","fileName":"PickleStepTestStep.java","lineNumber":51},{"declaringClass":"io.cucumber.core.runner.TestCase","methodName":"run","fileName":"TestCase.java","lineNumber":104},{"declaringClass":"io.cucumber.core.runner.Runner","methodName":"runPickle","fileName":"Runner.java","lineNumber":73},{"declaringClass":"io.cucumber.junit.FeatureRunner","methodName":"runChild","fileName":"FeatureRunner.java","lineNumber":135},{"declaringClass":"io.cucumber.junit.FeatureRunner","methodName":"runChild","fileName":"FeatureRunner.java","lineNumber":27},{"declaringClass":"io.cucumber.junit.CucumberSerenityRunner","methodName":"runChild","fileName":"CucumberSerenityRunner.java","lineNumber":258},{"declaringClass":"io.cucumber.junit.CucumberSerenityRunner","methodName":"runChild","fileName":"CucumberSerenityRunner.java","lineNumber":57},{"declaringClass":"org.eclipse.jdt.internal.junit4.runner.JUnit4TestReference","methodName":"run","fileName":"JUnit4TestReference.java","lineNumber":93},{"declaringClass":"org.eclipse.jdt.internal.junit.runner.TestExecution","methodName":"run","fileName":"TestExecution.java","lineNumber":40},{"declaringClass":"org.eclipse.jdt.internal.junit.runner.RemoteTestRunner","methodName":"runTests","fileName":"RemoteTestRunner.java","lineNumber":529},{"declaringClass":"org.eclipse.jdt.internal.junit.runner.RemoteTestRunner","methodName":"runTests","fileName":"RemoteTestRunner.java","lineNumber":756},{"declaringClass":"org.eclipse.jdt.internal.junit.runner.RemoteTestRunner","methodName":"run","fileName":"RemoteTestRunner.java","lineNumber":452},{"declaringClass":"org.eclipse.jdt.internal.junit.runner.RemoteTestRunner","methodName":"main","fileName":"RemoteTestRunner.java","lineNumber":210}],"rootCause":{"errorType":"org.openqa.selenium.TimeoutException","message":"Expected condition failed: waiting for By.xpath: //button[@id\u003d\u0027add-to-cart-sauce-labs-backpack\u0027] to be present (tried for 5 second(s) with 100 milliseconds interval)\nBuild info: version: \u00273.141.59\u0027, revision: \u0027e82be7d358\u0027, time: \u00272018-11-14T08:17:03\u0027\nSystem info: host: \u0027SSMED5CG1100JRZ\u0027, ip: \u0027192.168.1.145\u0027, os.name: \u0027Windows 10\u0027, os.arch: \u0027amd64\u0027, os.version: \u002710.0\u0027, java.version: \u00271.8.0_333\u0027\nDriver info: driver.version: unknown","stackTrace":[{"declaringClass":"com.sophos.semillero.tasks.NewProductListSauceDemo","methodName":"performAs","fileName":"NewProductListSauceDemo.java","lineNumber":28},{"declaringClass":"com.sophos.semillero.stepdefinitions.ProducListSauceDemoStepDefinitions","methodName":"elUsuarioSeEncuentraEnLaPaginaInventarios","fileName":"ProducListSauceDemoStepDefinitions.java","lineNumber":23},{"declaringClass":"io.cucumber.java.Invoker","methodName":"doInvoke","fileName":"Invoker.java","lineNumber":66},{"declaringClass":"io.cucumber.java.Invoker","methodName":"invoke","fileName":"Invoker.java","lineNumber":24},{"declaringClass":"io.cucumber.java.AbstractGlueDefinition","methodName":"invokeMethod","fileName":"AbstractGlueDefinition.java","lineNumber":47},{"declaringClass":"io.cucumber.java.JavaStepDefinition","methodName":"execute","fileName":"JavaStepDefinition.java","lineNumber":29},{"declaringClass":"io.cucumber.core.runner.CoreStepDefinition","methodName":"execute","fileName":"CoreStepDefinition.java","lineNumber":66},{"declaringClass":"io.cucumber.core.runner.PickleStepDefinitionMatch","methodName":"runStep","fileName":"PickleStepDefinitionMatch.java","lineNumber":63},{"declaringClass":"io.cucumber.core.runner.TestStep","methodName":"executeStep","fileName":"TestStep.java","lineNumber":92},{"declaringClass":"io.cucumber.core.runner.TestStep","methodName":"run","fileName":"TestStep.java","lineNumber":64},{"declaringClass":"io.cucumber.core.runner.PickleStepTestStep","methodName":"run","fileName":"PickleStepTestStep.java","lineNumber":51},{"declaringClass":"io.cucumber.core.runner.TestCase","methodName":"run","fileName":"TestCase.java","lineNumber":104},{"declaringClass":"io.cucumber.core.runner.Runner","methodName":"runPickle","fileName":"Runner.java","lineNumber":73},{"declaringClass":"io.cucumber.junit.FeatureRunner","methodName":"runChild","fileName":"FeatureRunner.java","lineNumber":135},{"declaringClass":"io.cucumber.junit.FeatureRunner","methodName":"runChild","fileName":"FeatureRunner.java","lineNumber":27},{"declaringClass":"io.cucumber.junit.CucumberSerenityRunner","methodName":"runChild","fileName":"CucumberSerenityRunner.java","lineNumber":258},{"declaringClass":"io.cucumber.junit.CucumberSerenityRunner","methodName":"runChild","fileName":"CucumberSerenityRunner.java","lineNumber":57},{"declaringClass":"org.eclipse.jdt.internal.junit4.runner.JUnit4TestReference","methodName":"run","fileName":"JUnit4TestReference.java","lineNumber":93},{"declaringClass":"org.eclipse.jdt.internal.junit.runner.TestExecution","methodName":"run","fileName":"TestExecution.java","lineNumber":40},{"declaringClass":"org.eclipse.jdt.internal.junit.runner.RemoteTestRunner","methodName":"runTests","fileName":"RemoteTestRunner.java","lineNumber":529},{"declaringClass":"org.eclipse.jdt.internal.junit.runner.RemoteTestRunner","methodName":"runTests","fileName":"RemoteTestRunner.java","lineNumber":756},{"declaringClass":"org.eclipse.jdt.internal.junit.runner.RemoteTestRunner","methodName":"run","fileName":"RemoteTestRunner.java","lineNumber":452},{"declaringClass":"org.eclipse.jdt.internal.junit.runner.RemoteTestRunner","methodName":"main","fileName":"RemoteTestRunner.java","lineNumber":210}]}},"testFailureClassname":"net.thucydides.core.webdriver.exceptions.ElementShouldBePresentException","testFailureMessage":"Expected condition failed: waiting for By.xpath: //button[@id\u003d\u0027add-to-cart-sauce-labs-backpack\u0027] to be present (tried for 5 second(s) with 100 milliseconds interval)\nBuild info: version: \u00273.141.59\u0027, revision: \u0027e82be7d358\u0027, time: \u00272018-11-14T08:17:03\u0027\nSystem info: host: \u0027SSMED5CG1100JRZ\u0027, ip: \u0027192.168.1.145\u0027, os.name: \u0027Windows 10\u0027, os.arch: \u0027amd64\u0027, os.version: \u002710.0\u0027, java.version: \u00271.8.0_333\u0027\nDriver info: driver.version: unknown","testFailureSummary":"FAILURE;net.thucydides.core.webdriver.exceptions.ElementShouldBePresentException;Expected condition failed: waiting for By.xpath: //button[@id\u003d\u0027add-to-cart-sauce-labs-backpack\u0027] to be present (tried for 5 second(s) with 100 milliseconds interval)\nBuild info: version: \u00273.141.59\u0027, revision: \u0027e82be7d358\u0027, time: \u00272018-11-14T08:17:03\u0027\nSystem info: host: \u0027SSMED5CG1100JRZ\u0027, ip: \u0027192.168.1.145\u0027, os.name: \u0027Windows 10\u0027, os.arch: \u0027amd64\u0027, os.version: \u002710.0\u0027, java.version: \u00271.8.0_333\u0027\nDriver info: driver.version: unknown;NewProductListSauceDemo.java","projectKey":"","annotatedResult":"FAILURE","sessionId":"d9b62fa6604e210251684d22d0904f03","driver":"chrome:standard_user","isManualTestingUpToDate":false,"manual":false,"testSource":"Cucumber","actors":[{"name":"standard_user","can":["browse the web"]}],"result":"FAILURE"}